prosegrinder/__init__.py
prosegrinder/__main__.py
prosegrinder/dictionary.py
prosegrinder/fragment.py
prosegrinder/fragment_container.py
prosegrinder/paragraph.py
prosegrinder/prose.py
prosegrinder/py.typed
prosegrinder/readability_scores.py
prosegrinder/sentence.py
prosegrinder/word.py
prosegrinder-1.4.3.dist-info/METADATA
prosegrinder-1.4.3.dist-info/WHEEL
prosegrinder-1.4.3.dist-info/entry_points.txt
prosegrinder-1.4.3.dist-info/licenses/LICENSE
prosegrinder-1.4.3.dist-info/RECORD
