Metadata-Version: 2.4
Name: prosegrinder
Version: 1.4.3
Summary: A text analytics library for prose fiction.
License: GPLv3
License-File: LICENSE
Keywords: text analytics,prose fiction,natural language processing,NLP,linguistics
Author: David L. Day
Author-email: david@davidlday.com
Requires-Python: >=3.9,<4.0
Classifier: Development Status :: 5 - Production/Stable
Classifier: Intended Audience :: Developers
Classifier: License :: OSI Approved :: GNU General Public License v3 (GPLv3)
Classifier: License :: Other/Proprietary License
Classifier: Natural Language :: English
Classifier: Operating System :: OS Independent
Classifier: Programming Language :: Python :: 3
Classifier: Programming Language :: Python :: 3.9
Classifier: Programming Language :: Python :: 3.10
Classifier: Programming Language :: Python :: 3.11
Classifier: Programming Language :: Python :: 3.12
Classifier: Programming Language :: Python :: 3.13
Classifier: Programming Language :: Python :: 3.14
Classifier: Topic :: Text Processing
Requires-Dist: click (>=8.1.3)
Requires-Dist: cmudict (>=1.0.11)
Requires-Dist: importlib-metadata (>=5.1.0)
Requires-Dist: narrative (>=1.1.1)
Requires-Dist: pointofview (>=1.0.2)
Requires-Dist: syllables (>=1.0.4)
Project-URL: Bug Tracker, https://github.com/prosegrinder/python-prosegrinder/issues
Project-URL: Homepage, https://github.com/prosegrinder/python-prosegrinder
Project-URL: Repository, https://github.com/prosegrinder/python-prosegrinder
